SeaSor/SeSo.py
SeaSor/__init__.py
SeaSor-0.1.3.4.dist-info/LICENSE
SeaSor-0.1.3.4.dist-info/METADATA
SeaSor-0.1.3.4.dist-info/WHEEL
SeaSor-0.1.3.4.dist-info/top_level.txt
SeaSor-0.1.3.4.dist-info/RECORD
